goecharger_api_lite/__init__.py
goecharger_api_lite/exception.py
goecharger_api_lite/goecharger_api_lite.py
goecharger_api_lite-1.5.1.dist-info/LICENSE
goecharger_api_lite-1.5.1.dist-info/METADATA
goecharger_api_lite-1.5.1.dist-info/WHEEL
goecharger_api_lite-1.5.1.dist-info/top_level.txt
goecharger_api_lite-1.5.1.dist-info/RECORD
