Metadata-Version: 2.1
Name: goecharger-api-lite
Version: 1.5.1
Summary: Lightweight Python API for accessing go-eCharger EV wallboxes using local HTTP API v2
Home-page: https://github.com/bkogler/goecharger-api-lite
Author: Bernhard Kogler
Author-email: bernhard.kogler@supersonnig.org
License: MIT
Keywords: go-e EV wallbox electric charger Gemini flex HOMEfix HOME+ HTTP API v2
Classifier: Development Status :: 5 - Production/Stable
Classifier: Programming Language :: Python :: 3
Classifier: License :: OSI Approved :: MIT License
Classifier: Operating System :: OS Independent
Requires-Python: >=3.10
License-File: LICENSE
Requires-Dist: aiohttp
Requires-Dist: aiodns
